gbm_sim/__init__.py
gbm_sim/cli.py
gbm_sim/core.py
gbm_sim/simulate.py
gbm_sim/__pycache__/__init__.cpython-312.pyc
gbm_sim/__pycache__/cli.cpython-312.pyc
gbm_sim/__pycache__/core.cpython-312.pyc
gbm_sim/__pycache__/simulate.cpython-312.pyc
gbm_sim-1.0.0.dist-info/METADATA
gbm_sim-1.0.0.dist-info/WHEEL
gbm_sim-1.0.0.dist-info/entry_points.txt
gbm_sim-1.0.0.dist-info/top_level.txt
gbm_sim-1.0.0.dist-info/RECORD
