Metadata-Version: 2.4
Name: gbm_sim
Version: 1.0.0
Summary: A Python package for simulating Geometric Brownian Motion.
Author-email: Your Name <your.email@example.com>, Harvey <boris.bolliet@gmail.com>
Project-URL: Documentation, https://your-readthedocs-url-here
Project-URL: Source, https://github.com/yourusername/gbm_sim_package
Project-URL: Issues, https://github.com/yourusername/gbm_sim_package/issues
Keywords: Brownian Motion,simulation
Classifier: Development Status :: 4 - Beta
Classifier: Intended Audience :: Science/Research
Classifier: License :: OSI Approved :: MIT License
Classifier: Programming Language :: Python :: 3
Classifier: Topic :: Software Development :: Libraries
Requires-Python: >=3.9
Requires-Dist: numpy
Requires-Dist: pandas
Requires-Dist: argparse
Requires-Dist: matplotlib
